[ {
  "date" : "20150223",
  "summary" : [ {
    "activity" : "walking",
    "group" : "walking",
    "duration" : 8457.0,
    "distance" : 4228.0,
    "steps" : 8457,
    "calories" : 263
  } ],
  "segments" : [ {
    "type" : "move",
    "startTime" : "20150223T071530+0100",
    "endTime" : "20150224T084533+0100",
    "activities" : [ {
      "activity" : "walking",
      "group" : "walking",
      "manual" : false,
      "startTime" : "20150223T123327+0100",
      "endTime" : "20150223T132923+0100",
      "duration" : 3356.0,
      "distance" : 1678.0,
      "steps" : 3356,
      "calories" : 104,
      "trackPoints" : [ ]
    }, {
      "activity" : "walking",
      "group" : "walking",
      "manual" : false,
      "startTime" : "20150223T223459+0100",
      "endTime" : "20150224T000000+0100",
      "duration" : 5101.0,
      "distance" : 2550.0,
      "steps" : 5101,
      "calories" : 158,
      "trackPoints" : [ ]
    } ],
    "lastUpdate" : "20150225T091539Z"
  } ],
  "caloriesIdle" : 1790,
  "lastUpdate" : "20150225T091539Z"
}, {
  "date" : "20150224",
  "summary" : [ {
    "activity" : "walking",
    "group" : "walking",
    "duration" : 2707.0,
    "distance" : 1354.0,
    "steps" : 2707,
    "calories" : 84
  } ],
  "segments" : [ {
    "type" : "move",
    "startTime" : "20150223T071530+0100",
    "endTime" : "20150224T084533+0100",
    "activities" : [ {
      "activity" : "walking",
      "group" : "walking",
      "manual" : false,
      "startTime" : "20150224T000000+0100",
      "endTime" : "20150224T004507+0100",
      "duration" : 2707.0,
      "distance" : 1354.0,
      "steps" : 2707,
      "calories" : 84,
      "trackPoints" : [ ]
    } ],
    "lastUpdate" : "20150225T091539Z"
  } ],
  "caloriesIdle" : 1790,
  "lastUpdate" : "20150225T091539Z"
}, {
  "date" : "20150225",
  "summary" : [ {
    "activity" : "walking",
    "group" : "walking",
    "duration" : 2878.0,
    "distance" : 1440.0,
    "steps" : 2878,
    "calories" : 90
  } ],
  "segments" : [ {
    "type" : "move",
    "startTime" : "20150224T084533+0100",
    "endTime" : "20150225T110909+0100",
    "activities" : [ {
      "activity" : "walking",
      "group" : "walking",
      "manual" : false,
      "startTime" : "20150225T012148+0100",
      "endTime" : "20150225T012737+0100",
      "duration" : 349.0,
      "distance" : 175.0,
      "steps" : 349,
      "calories" : 11,
      "trackPoints" : [ ]
    } ],
    "lastUpdate" : "20150226T123249Z"
  }, {
    "type" : "move",
    "startTime" : "20150225T110909+0100",
    "endTime" : "20150226T134223+0100",
    "activities" : [ {
      "activity" : "walking",
      "group" : "walking",
      "manual" : false,
      "startTime" : "20150225T112726+0100",
      "endTime" : "20150225T120935+0100",
      "duration" : 2529.0,
      "distance" : 1265.0,
      "steps" : 2529,
      "calories" : 79,
      "trackPoints" : [ ]
    } ],
    "lastUpdate" : "20150227T151539Z"
  } ],
  "caloriesIdle" : 1790,
  "lastUpdate" : "20150227T151539Z"
}, {
  "date" : "20150226",
  "summary" : [ {
    "activity" : "walking",
    "group" : "walking",
    "duration" : 9436.0,
    "distance" : 4718.0,
    "steps" : 9436,
    "calories" : 293
  } ],
  "segments" : [ {
    "type" : "move",
    "startTime" : "20150225T110909+0100",
    "endTime" : "20150226T134223+0100",
    "activities" : [ {
      "activity" : "walking",
      "group" : "walking",
      "manual" : false,
      "startTime" : "20150226T002911+0100",
      "endTime" : "20150226T011433+0100",
      "duration" : 2722.0,
      "distance" : 1361.0,
      "steps" : 2722,
      "calories" : 85,
      "trackPoints" : [ ]
    }, {
      "activity" : "walking",
      "group" : "walking",
      "manual" : false,
      "startTime" : "20150226T124056+0100",
      "endTime" : "20150226T134224+0100",
      "duration" : 3688.0,
      "distance" : 1844.0,
      "steps" : 3688,
      "calories" : 115,
      "trackPoints" : [ ]
    } ],
    "lastUpdate" : "20150227T151539Z"
  }, {
    "type" : "move",
    "startTime" : "20150226T134223+0100",
    "endTime" : "20150227T144402+0100",
    "activities" : [ {
      "activity" : "walking",
      "group" : "walking",
      "manual" : false,
      "startTime" : "20150226T134223+0100",
      "endTime" : "20150226T143249+0100",
      "duration" : 3026.0,
      "distance" : 1513.0,
      "steps" : 3026,
      "calories" : 94,
      "trackPoints" : [ ]
    } ],
    "lastUpdate" : "20150228T144543Z"
  } ],
  "caloriesIdle" : 1790,
  "lastUpdate" : "20150228T144543Z"
}, {
  "date" : "20150228",
  "summary" : [ {
    "activity" : "walking",
    "group" : "walking",
    "duration" : 586.0,
    "distance" : 293.0,
    "steps" : 586,
    "calories" : 18
  } ],
  "segments" : [ {
    "type" : "move",
    "startTime" : "20150228T151509+0100",
    "endTime" : "20150301T165025+0100",
    "activities" : [ {
      "activity" : "walking",
      "group" : "walking",
      "manual" : false,
      "startTime" : "20150228T154548+0100",
      "endTime" : "20150228T155534+0100",
      "duration" : 586.0,
      "distance" : 293.0,
      "steps" : 586,
      "calories" : 18,
      "trackPoints" : [ ]
    } ],
    "lastUpdate" : "20150301T155030Z"
  } ],
  "caloriesIdle" : 1790,
  "lastUpdate" : "20150301T155030Z"
}, {
  "date" : "20150301",
  "summary" : [ {
    "activity" : "walking",
    "group" : "walking",
    "duration" : 3780.0,
    "distance" : 1890.0,
    "steps" : 3780,
    "calories" : 117
  } ],
  "segments" : [ {
    "type" : "move",
    "startTime" : "20150228T151509+0100",
    "endTime" : "20150301T165025+0100",
    "activities" : [ {
      "activity" : "walking",
      "group" : "walking",
      "manual" : false,
      "startTime" : "20150301T154704+0100",
      "endTime" : "20150301T165004+0100",
      "duration" : 3780.0,
      "distance" : 1890.0,
      "steps" : 3780,
      "calories" : 117,
      "trackPoints" : [ ]
    } ],
    "lastUpdate" : "20150301T155030Z"
  } ],
  "caloriesIdle" : 1790,
  "lastUpdate" : "20150301T155030Z"
} ]